numpybd/__init__.py
numpybd/loss.py
torchbd/__init__.py
torchbd/loss.py
torchbd/nn.py
beta_divergence_metrics-0.0.2.dist-info/LICENSE
beta_divergence_metrics-0.0.2.dist-info/METADATA
beta_divergence_metrics-0.0.2.dist-info/WHEEL
beta_divergence_metrics-0.0.2.dist-info/top_level.txt
beta_divergence_metrics-0.0.2.dist-info/RECORD
