Metadata-Version: 2.1
Name: beta-divergence-metrics
Version: 0.0.2
Summary: NumPy and PyTorch implementations of the beta-divergence loss.
Home-page: https://github.com/wecarsoniv/beta-divergence-metrics
Author: Billy Carson
Author-email: williamcarsoniv@gmail.com
License: UNKNOWN
Project-URL: Issue Tracker, https://github.com/wecarsoniv/beta-divergence-metrics/issues
Keywords: numpybd,torchbd,numpy,pytorch,beta-divergence,beta divergence,beta,divergence,beta-loss,beta loss,loss,beta-distance,beta distance,distance,itakura-saito divergence,itakura saito divergence,is-divergence,is divergence,itakura-saito,itakura saito,itakura,saito,kullback-leibler divergence,kullback leibler divergence,kl divergence,kl,kullback-leibler,kullback,leibler
Platform: UNKNOWN
Classifier: Programming Language :: Python :: 3
Classifier: License :: OSI Approved :: MIT License
Classifier: Operating System :: OS Independent
